nshrunner/.nshconfig.generated.json
nshrunner/__init__.py
nshrunner/_config.py
nshrunner/_env.py
nshrunner/_runner.py
nshrunner/_seed.py
nshrunner/_submit/_util.py
nshrunner/_submit/screen.py
nshrunner/_submit/slurm.py
nshrunner/_util/code_saving.py
nshrunner/_util/environment.py
nshrunner/_util/kv.py
nshrunner/_util/print_environment_info.py
nshrunner/backends/screen.py
nshrunner/backends/slurm.py
nshrunner/configs/.gitattributes
nshrunner/configs/Config_typed_dict.py
nshrunner/configs/__init__.py
nshrunner/configs/_config/Config_typed_dict.py
nshrunner/configs/_config/SeedConfig_typed_dict.py
nshrunner/configs/_config/__init__.py
nshrunner/configs/_runner/Config_typed_dict.py
nshrunner/configs/_runner/__init__.py
nshrunner/configs/_seed/SeedConfig_typed_dict.py
nshrunner/configs/_seed/__init__.py
nshrunner/configs/backends/__init__.py
nshrunner/configs/backends/screen/LoggingConfig_typed_dict.py
nshrunner/configs/backends/screen/ScreenBackendConfig_typed_dict.py
nshrunner/configs/backends/screen/__init__.py
nshrunner/configs/backends/slurm/SlurmBackendConfig_typed_dict.py
nshrunner/configs/backends/slurm/SlurmMailConfig_typed_dict.py
nshrunner/configs/backends/slurm/__init__.py
nshrunner/picklerunner/_util.py
nshrunner/picklerunner/create.py
nshrunner/picklerunner/main.py
nshrunner/session.py
nshrunner/submission.py
nshrunner/wrapper_fns.py
nshrunner-1.6.0.dist-info/LICENSE
nshrunner-1.6.0.dist-info/METADATA
nshrunner-1.6.0.dist-info/WHEEL
nshrunner-1.6.0.dist-info/entry_points.txt
nshrunner-1.6.0.dist-info/RECORD
