Metadata-Version: 2.3
Name: nshrunner
Version: 1.6.0
Summary: 
Author: Nima Shoghi
Author-email: nimashoghi@gmail.com
Requires-Python: >=3.9,<4.0
Classifier: Programming Language :: Python :: 3
Classifier: Programming Language :: Python :: 3.9
Classifier: Programming Language :: Python :: 3.10
Classifier: Programming Language :: Python :: 3.11
Classifier: Programming Language :: Python :: 3.12
Classifier: Programming Language :: Python :: 3.13
Provides-Extra: extra
Requires-Dist: GitPython
Requires-Dist: cloudpickle
Requires-Dist: deepmerge
Requires-Dist: flufl.lock
Requires-Dist: nshconfig
Requires-Dist: nshsnap (>=0.14)
Requires-Dist: tqdm
Requires-Dist: typing-extensions
Project-URL: Homepage, https://github.com/nimashoghi/nshrunner
